README.md
setup.py
apkpuller/apkpuller.py
apkpuller.egg-info/PKG-INFO
apkpuller.egg-info/SOURCES.txt
apkpuller.egg-info/dependency_links.txt
apkpuller.egg-info/entry_points.txt
apkpuller.egg-info/requires.txt
apkpuller.egg-info/top_level.txt