Metadata-Version: 2.1
Name: apkpuller
Version: 1.0.1
Summary: Tool extract APKs from device to desktop directories
Home-page: https://github.com/abeljm/APKPuller
Author: Avelino Navarro
Author-email: abeljm2017@gmail.com
License: UNKNOWN
Platform: UNKNOWN
Classifier: Programming Language :: Python :: 3
Classifier: Programming Language :: Python :: 3.9
Classifier: License :: OSI Approved :: GNU General Public License v3 (GPLv3)
